aok/__init__.py
aok/_definitions.py
aok/_operations.py
aok/_types.py
aok/_utils.py
aok/comparisons/__init__.py
aok/comparisons/_basics.py
aok/comparisons/_dicts.py
aok/comparisons/_lists.py
aok/comparisons/_nullish.py
aok/comparisons/_strings.py
aok-0.3.4.dist-info/WHEEL
aok-0.3.4.dist-info/METADATA
aok-0.3.4.dist-info/RECORD
