Metadata-Version: 2.1
Name: aok
Version: 0.3.4
Summary: Complex dictionary comparisons to simplify testing.
Home-page: https://gitlab.com/rocket-boosters/a-ok
License: MIT
Keywords: testing,comparisons
Author: Scott Ernst
Author-email: swernst@gmail.com
Requires-Python: >=3.8,<4.0
Classifier: Development Status :: 4 - Beta
Classifier: Intended Audience :: Developers
Classifier: License :: OSI Approved :: MIT License
Classifier: Programming Language :: Python :: 3
Classifier: Programming Language :: Python :: 3.10
Classifier: Programming Language :: Python :: 3.8
Classifier: Programming Language :: Python :: 3.9
Classifier: Topic :: Software Development :: Testing
Classifier: Topic :: Software Development :: Testing :: Unit
Classifier: Topic :: Utilities
Classifier: Typing :: Typed
Requires-Dist: PyYAML (>=5.3.1)
Requires-Dist: toml (>=0.10.2)
Project-URL: Documentation, https://gitlab.com/rocket-boosters/a-ok
Project-URL: Repository, https://gitlab.com/rocket-boosters/a-ok
